Metadata-Version: 2.1
Name: masksemi
Version: 0.0.1
Summary: Code for converting a list of labels in a scikit-like semi-supervised labels.
Home-page: https://github.com/caiocarneloz/masksemi
Author: Caio Carneloz
License: MIT License
Keywords: semi-supervised,label,preprocessing
Platform: UNKNOWN
